crowdstrike_foundry/__init__.py
crowdstrike_foundry/telemetry.py
crowdstrike_foundry-20.3.0.dist-info/METADATA
crowdstrike_foundry-20.3.0.dist-info/WHEEL
crowdstrike_foundry-20.3.0.dist-info/top_level.txt
crowdstrike_foundry-20.3.0.dist-info/RECORD
