Metadata-Version: 2.1
Name: crowdstrike-foundry
Version: 20.3.0
Summary: CrowdStrike Foundry Integration
Home-page: https://github.com/yourusername/crowdstrike-foundry
Author: Your Name
Author-email: your.email@example.com
Classifier: Programming Language :: Python :: 3
Classifier: License :: OSI Approved :: MIT License
Classifier: Operating System :: OS Independent
Requires-Python: >=3.6
Requires-Dist: requests>=2.25.0
